Historic_Crypto/Cryptocurrencies.py
Historic_Crypto/HistoricalData.py
Historic_Crypto/LiveCryptoData.py
Historic_Crypto/__init__.py
Historic_Crypto-0.1.6.dist-info/LICENSE
Historic_Crypto-0.1.6.dist-info/METADATA
Historic_Crypto-0.1.6.dist-info/WHEEL
Historic_Crypto-0.1.6.dist-info/top_level.txt
Historic_Crypto-0.1.6.dist-info/RECORD
