Metadata-Version: 2.1
Name: Historic_Crypto
Version: 0.1.6
Summary: An open source Python library for scraping Historical Cryptocurrency data.
Home-page: https://github.com/David-Woroniuk/Historic_Crypto
Author: David Woroniuk
Author-email: david.j.woroniuk@durham.ac.uk
License: MIT License
Platform: UNKNOWN
License-File: LICENSE
